random_strings.py
random_strings-0.1.0.dist-info/LICENSE.txt
random_strings-0.1.0.dist-info/METADATA
random_strings-0.1.0.dist-info/WHEEL
random_strings-0.1.0.dist-info/top_level.txt
random_strings-0.1.0.dist-info/RECORD
