Metadata-Version: 2.1
Name: random-strings
Version: 0.1.0
Summary: strings that are ✨ random ✨
Home-page: https://github.com/dheerajreal/random-strings/
License: MIT
Project-URL: Bug Reports, https://github.com/dheerajreal/random-strings/issues
Project-URL: Source, https://github.com/dheerajreal/random-strings/
Keywords: random,strings,utilities,security
Platform: UNKNOWN
Classifier: Development Status :: 3 - Alpha
Classifier: Intended Audience :: Developers
Classifier: Topic :: Software Development :: Libraries :: Python Modules
Classifier: License :: OSI Approved :: MIT License
Classifier: Programming Language :: Python :: 3
Classifier: Programming Language :: Python :: 3.6
Classifier: Programming Language :: Python :: 3.7
Classifier: Programming Language :: Python :: 3.8
Classifier: Programming Language :: Python :: 3.9
Classifier: Programming Language :: Python :: 3 :: Only
Requires-Python: >=3.6, <4
License-File: LICENSE.txt
